threadmycode/__init__.py
threadmycode-0.0.7.dist-info/LICENSE
threadmycode-0.0.7.dist-info/METADATA
threadmycode-0.0.7.dist-info/WHEEL
threadmycode-0.0.7.dist-info/top_level.txt
threadmycode-0.0.7.dist-info/RECORD
