Metadata-Version: 2.1
Name: threadmycode
Version: 0.0.7
Summary: Add python code in threading mode
Home-page: https://github.com/seerajudeensm/threadmycode
Author: Seeerajudeen
Author-email: seerajudeensm@gmail.com
License: UNKNOWN
Project-URL: Bug Tracker, https://github.com/seerajudeensm/threadmycode/issues
Platform: UNKNOWN
Classifier: Programming Language :: Python :: 3
Classifier: License :: OSI Approved :: MIT License
Classifier: Operating System :: OS Independent
Requires-Python: >=3.6
License-File: LICENSE
